{
  "users": [
    {
      "username": "Mr_Fernanski",
      "password": "admin123",
      "isAdmin": true,
      "inventory": {
        "rarities": {},
        "potions": {},
        "items": {}
      },
      "activePotions": [],
      "coins": 10000,
      "lastSpin": 0,
      "joinDate": "2025-10-22T00:00:00.000Z"
    }
  ],
  "codes": [
    {
      "code": "WELCOME17",
      "reward": {
        "type": "coins",
        "amount": 500
      },
      "usedBy": []
    },
    {
      "code": "ALPHA2025",
      "reward": {
        "type": "coins",
        "amount": 1000
      },
      "usedBy": []
    },
    {
      "code": "POTION",
      "reward": {
        "type": "potion",
        "potion": "luck1"
      },
      "usedBy": []
    }
  ],
  "announcements": [],
  "events": [],
  "chatMessages": [],
  "aaEvents": []
}
